{
  "app_wallet": {
    "playground": "bxkhk-6yaaa-aaaal-ai6va-cai",
    "production": "5fu67-giaaa-aaaal-ajbla-cai",
    "testing": "l3uq6-ryaaa-aaaal-adu2a-cai"
  },
  "control_panel": {
    "playground": "b6jmw-iqaaa-aaaal-ai6uq-cai",
    "production": "5mxvd-qaaaa-aaaal-ajbkq-cai",
    "testing": "lotbt-qqaaa-aaaal-aduzq-cai"
  },
  "app_marketing": {
    "production": "TBD"
  },
  "docs_portal": {
    "production": "bp6mw-eqaaa-aaaac-ahroq-cai"
  },
  "wasm_chunk_store": {
    "playground": "lwcm6-3aaaa-aaaam-qb7ba-cai",
    "production": "f2mu6-kiaaa-aaaam-advhq-cai"
  }
}